mobileconfig/__init__.py
mobileconfig/__main__.py
mobileconfig/mobileconfig.py
mobileconfig-1.1.1.dist-info/LICENSE
mobileconfig-1.1.1.dist-info/METADATA
mobileconfig-1.1.1.dist-info/WHEEL
mobileconfig-1.1.1.dist-info/entry_points.txt
mobileconfig-1.1.1.dist-info/top_level.txt
mobileconfig-1.1.1.dist-info/RECORD
