Metadata-Version: 2.1
Name: mobileconfig
Version: 1.1.1
Summary: Parse .mobileconfig files
Home-page: https://github.com/yotamolenik/mobileconfig
Author: Yotam
Author-email: yotamolenik@gmail.com
License: GNU GENERAL PUBLIC LICENSE - Version 3, 29 June 2007
Project-URL: mobileconfig, https://github.com/yotamolenik/mobileconfig
Classifier: Programming Language :: Python :: 3.7
Classifier: Programming Language :: Python :: 3.8
Classifier: Programming Language :: Python :: 3.9
Classifier: Programming Language :: Python :: 3.10
License-File: LICENSE
Requires-Dist: click
Requires-Dist: mdutils
